SeREGen/__init__.py
SeREGen/_saving.py
SeREGen/comparative_encoder.py
SeREGen/dataset_builder.py
SeREGen/distance.py
SeREGen/encoders.py
SeREGen/kmer_compression.py
SeREGen/kmers.py
SeREGen/pipeline.py
SeREGen/visualize.py
SeREGen-0.1.2.dist-info/LICENSE
SeREGen-0.1.2.dist-info/METADATA
SeREGen-0.1.2.dist-info/WHEEL
SeREGen-0.1.2.dist-info/top_level.txt
SeREGen-0.1.2.dist-info/RECORD
