Metadata-Version: 2.1
Name: SeREGen
Version: 0.1.2
Summary: Automated, cross-platform Representative Embedding generation.
Author-email: Nikhil Kalidasu <srikarnikhil.kalidasu@gmail.com>
Project-URL: Homepage, https://github.com/nik875/SeREGen
Project-URL: Issues, https://github.com/nik875/SeREGen/issues
Classifier: Programming Language :: Python :: 3
Classifier: License :: OSI Approved :: GNU General Public License (GPL)
Classifier: Operating System :: OS Independent
Requires-Python: >=3.9
License-File: LICENSE
Requires-Dist: numpy >=1.21.2
Requires-Dist: tqdm >=4.64.2
Requires-Dist: torch >=2.3.1
Requires-Dist: torchtext >=0.17.0
Requires-Dist: torchinfo >=1.8.0
Requires-Dist: scikit-learn >=1.3.0
Requires-Dist: matplotlib >=3.4.3
Requires-Dist: biopython >=1.79
Requires-Dist: pandas >=1.3.3
Requires-Dist: scipy >=1.10.1
Requires-Dist: rdkit >=2023.3.3
Requires-Dist: Levenshtein >=0.25.1
Requires-Dist: geomstats >=2.7.0
